vocabsieve/__init__.py
vocabsieve/__main__.py
vocabsieve/audio_player.py
vocabsieve/cached_get.py
vocabsieve/constants.py
vocabsieve/dictformats.py
vocabsieve/dictionary.py
vocabsieve/format.py
vocabsieve/global_names.py
vocabsieve/lemmatizer.py
vocabsieve/local_dictionary.py
vocabsieve/main.py
vocabsieve/models.py
vocabsieve/record.py
vocabsieve/stats.py
vocabsieve/tools.py
vocabsieve/uncaught_hook.py
vocabsieve/vsnt.py
vocabsieve/analyzer/BookAnalyzer.py
vocabsieve/analyzer/__init__.py
vocabsieve/analyzer/utils.py
vocabsieve/config/__init__.py
vocabsieve/config/anki_tab.py
vocabsieve/config/base_tab.py
vocabsieve/config/config_dialog.py
vocabsieve/config/dictmanager.py
vocabsieve/config/fieldmatcher.py
vocabsieve/config/general_tab.py
vocabsieve/config/interface_tab.py
vocabsieve/config/misc_tab.py
vocabsieve/config/network_tab.py
vocabsieve/config/processing_tab.py
vocabsieve/config/source_tab.py
vocabsieve/config/tracking_tab.py
vocabsieve/config/word_rules_editor.py
vocabsieve/contentmanager/__init__.py
vocabsieve/contentmanager/contentmanager.py
vocabsieve/contentmanager/dialog.py
vocabsieve/contentmanager/utils.py
vocabsieve/importer/AutoTextImporter.py
vocabsieve/importer/AutoTextVisualizer.py
vocabsieve/importer/BatchNotePreviewer.py
vocabsieve/importer/GenericImporter.py
vocabsieve/importer/KindleVocabImporter.py
vocabsieve/importer/KoreaderVocabImporter.py
vocabsieve/importer/WordListImporter.py
vocabsieve/importer/__init__.py
vocabsieve/importer/models.py
vocabsieve/importer/utils.py
vocabsieve/reader/__init__.py
vocabsieve/reader/server.py
vocabsieve/reader/utils.py
vocabsieve/reader/static/bulma.min.css
vocabsieve/reader/static/epub.min.js
vocabsieve/reader/static/jquery-3.6.0.min.js
vocabsieve/reader/static/jszip.min.js
vocabsieve/reader/static/normalize.min.css
vocabsieve/reader/static/reader.css
vocabsieve/reader/static/reader.js
vocabsieve/reader/static/sanitize-html.min.js
vocabsieve/reader/templates/home.html
vocabsieve-0.12.5.dist-info/licenses/LICENSE
vocabsieve-0.12.5.dist-info/METADATA
vocabsieve-0.12.5.dist-info/WHEEL
vocabsieve-0.12.5.dist-info/entry_points.txt
vocabsieve-0.12.5.dist-info/top_level.txt
vocabsieve-0.12.5.dist-info/RECORD
