Metadata-Version: 2.4
Name: vocabsieve
Version: 0.12.5
Summary: A simple, effective sentence mining tool.
Home-page: https://github.com/FreeLanguageTools/vocabsieve
Author: FreeLanguageTools
Author-email: pypi@5f37.8shield.net
Classifier: Programming Language :: Python :: 3
Classifier: License :: OSI Approved :: GNU General Public License v3 (GPLv3)
Classifier: Operating System :: OS Independent
Classifier: Environment :: X11 Applications :: Qt
Requires-Python: >=3.11
License-File: LICENSE
Requires-Dist: lxml
Requires-Dist: PyQt5
Requires-Dist: requests
Requires-Dist: beautifulsoup4
Requires-Dist: simplemma
Requires-Dist: pystardict
Requires-Dist: bidict
Requires-Dist: flask
Requires-Dist: charset-normalizer
Requires-Dist: slpp
Requires-Dist: mobi
Requires-Dist: sentence_splitter
Requires-Dist: pymorphy3
Requires-Dist: pyqtgraph
Requires-Dist: pymorphy3-dicts-ru
Requires-Dist: pymorphy3-dicts-uk
Requires-Dist: ebooklib
Requires-Dist: pyqtdarktheme-fork
Requires-Dist: pysubs2
Requires-Dist: markdownify
Requires-Dist: markdown
Requires-Dist: python-lzo
Requires-Dist: readmdict
Requires-Dist: loguru
Requires-Dist: packaging
Requires-Dist: typing_extensions
Requires-Dist: waitress
Dynamic: license-file
